opencti_excel_uploader/__init__.py
opencti_excel_uploader/__main__.py
opencti_excel_uploader/models.py
opencti_excel_uploader/xlsx_utils.py
opencti_excel_uploader-1.1.0.dist-info/METADATA
opencti_excel_uploader-1.1.0.dist-info/WHEEL
opencti_excel_uploader-1.1.0.dist-info/entry_points.txt
opencti_excel_uploader-1.1.0.dist-info/top_level.txt
opencti_excel_uploader-1.1.0.dist-info/RECORD
