Metadata-Version: 2.1
Name: opencti-excel-uploader
Version: 1.1.0
Summary: Creates workbench files from excel files for Opencti
License: MIT
Classifier: Programming Language :: Python :: 3
Classifier: License :: OSI Approved :: MIT License
Classifier: Operating System :: OS Independent
Requires-Dist: pycti <7.0.0,>=6.0.9
Requires-Dist: pandas <3.0.0,>=2.2.2
Requires-Dist: openpyxl <4.0.0,>=3.1.2
Requires-Dist: python-dotenv <2.0.0,>=1.0.1
Requires-Dist: urllib3 <3.0.0,>=2.2.1
